space_cli/__init__.py
space_cli/index_store.py
space_cli/space_analyzer.py
space_cli/spacecli_class.py
myspace_cli-1.7.0.dist-info/METADATA
myspace_cli-1.7.0.dist-info/WHEEL
myspace_cli-1.7.0.dist-info/entry_points.txt
myspace_cli-1.7.0.dist-info/top_level.txt
myspace_cli-1.7.0.dist-info/RECORD
