Metadata-Version: 2.4
Name: myspace-cli
Version: 1.7.0
Summary: A macOS disk space analysis CLI: health, index, app usage, big files.
Author-email: Your Name <you@example.com>
License: MIT
Project-URL: Homepage, https://github.com/kennyz/space-cli
Project-URL: Issues, https://github.com/kennyz/space-cli/issues
Keywords: disk,space,cleanup,macos,cli
Classifier: Programming Language :: Python :: 3
Classifier: License :: OSI Approved :: MIT License
Classifier: Operating System :: MacOS
Classifier: Environment :: Console
Classifier: Topic :: System :: Filesystems
Requires-Python: >=3.8
Provides-Extra: mcp
Requires-Dist: mcp<2,>=1; extra == "mcp"
